attpc_engine-0.9.0.dist-info/METADATA
attpc_engine-0.9.0.dist-info/WHEEL
attpc_engine-0.9.0.dist-info/entry_points.txt
attpc_engine-0.9.0.dist-info/licenses/LICENSE
attpc_engine/__init__.py
attpc_engine/detector/__init__.py
attpc_engine/detector/beam_pads.py
attpc_engine/detector/constants.py
attpc_engine/detector/data/__init__.py
attpc_engine/detector/data/pad_grid.npz
attpc_engine/detector/data/pad_scale.csv
attpc_engine/detector/data/padxy.csv
attpc_engine/detector/pairing.py
attpc_engine/detector/parameters.py
attpc_engine/detector/response.py
attpc_engine/detector/simulator.py
attpc_engine/detector/solver.py
attpc_engine/detector/transporter.py
attpc_engine/detector/typed_dict.py
attpc_engine/detector/writer.py
attpc_engine/kinematics/__init__.py
attpc_engine/kinematics/angle.py
attpc_engine/kinematics/convert_kinematics.py
attpc_engine/kinematics/excitation.py
attpc_engine/kinematics/pipeline.py
attpc_engine/kinematics/reaction.py
attpc_engine-0.9.0.dist-info/RECORD
