Metadata-Version: 2.1
Name: attpc_engine
Version: 0.9.0
Summary: AT-TPC Monte-Carlo simulation engine
Author-Email: Gordon McCann <gordonmccann215@gmail.com>, Zach Serikow <zachserikow@gmail.com>
License:                     GNU GENERAL PUBLIC LICENSE
Classifier: Intended Audience :: Science/Research
Classifier: License :: OSI Approved :: GNU General Public License v3 (GPLv3)
Classifier: Operating System :: Microsoft :: Windows :: Windows 10
Classifier: Operating System :: Microsoft :: Windows :: Windows 11
Classifier: Operating System :: MacOS
Classifier: Operating System :: POSIX :: Linux
Classifier: Programming Language :: Python :: 3
Classifier: Programming Language :: Python :: 3.10
Classifier: Programming Language :: Python :: 3.11
Classifier: Programming Language :: Python :: 3.12
Classifier: Topic :: Scientific/Engineering :: Physics
Classifier: Typing :: Typed
Project-URL: Documentation, https://attpc.github.io/attpc_engine
Project-URL: Repository, https://github.com/ATTPC/attpc_engine
Project-URL: Issues, https://github.com/ATTPC/attpc_engine/issues
Requires-Python: <3.13,>=3.10
Requires-Dist: spyral-utils>=2.0.0
Requires-Dist: h5py>=3.11.0
Requires-Dist: numba>=0.61.0
Requires-Dist: tqdm>=4.66.4
Requires-Dist: scipy>=1.14.0
